kdrag/__init__.py
kdrag/all.py
kdrag/config.py
kdrag/contrib/__init__.py
kdrag/contrib/absint/knownbit.py
kdrag/contrib/data_modulo/__init__.py
kdrag/contrib/expr/__init__.py
kdrag/contrib/fast/.gitignore
kdrag/contrib/fast/Makefile
kdrag/contrib/fast/__init__.py
kdrag/contrib/fast/fast.c
kdrag/contrib/fast/fast.h
kdrag/contrib/fast/tests.c
kdrag/contrib/hoare.py
kdrag/contrib/junk_drawer/algebra.py
kdrag/contrib/junk_drawer/generic.py
kdrag/contrib/junk_drawer/list.py
kdrag/contrib/pcode/README.md
kdrag/contrib/pcode/__init__.py
kdrag/contrib/pcode/__main__.py
kdrag/contrib/pcode/asmspec.py
kdrag/contrib/yosys/__init__.py
kdrag/datatype.py
kdrag/hypothesis.py
kdrag/kernel.py
kdrag/modal.py
kdrag/notation.py
kdrag/parsers/__init__.py
kdrag/parsers/microlean.py
kdrag/parsers/sexp.py
kdrag/parsers/smtlib.py
kdrag/parsers/tptp.py
kdrag/parsers/trs.py
kdrag/printers/__init__.py
kdrag/printers/c.py
kdrag/printers/lean.py
kdrag/printers/llvm.py
kdrag/printers/rust.py
kdrag/printers/verilog.py
kdrag/property.py
kdrag/reflect.py
kdrag/rewrite.py
kdrag/smt.py
kdrag/smt.pyi
kdrag/solvers/.gitignore
kdrag/solvers/__init__.py
kdrag/solvers/__main__.py
kdrag/solvers/aprove.py
kdrag/solvers/datalog.py
kdrag/solvers/egglog.py
kdrag/solvers/egraph.py
kdrag/solvers/install.sh
kdrag/solvers/kb/__init__.py
kdrag/solvers/kb/multiset.py
kdrag/solvers/kb/string.py
kdrag/solvers/ljt.py
kdrag/solvers/prolog.py
kdrag/solvers/sympy.py
kdrag/tactics.py
kdrag/tele.py
kdrag/theories/__init__.py
kdrag/theories/algebra/__init__.py
kdrag/theories/algebra/category.py
kdrag/theories/algebra/filter.py
kdrag/theories/algebra/group.py
kdrag/theories/algebra/kleene.py
kdrag/theories/algebra/lattice.py
kdrag/theories/algebra/ordering.py
kdrag/theories/algebra/sqmatrix.py
kdrag/theories/algebra/topology.py
kdrag/theories/algebra/vector.py
kdrag/theories/bitvec.py
kdrag/theories/bool.py
kdrag/theories/fixed.py
kdrag/theories/float.py
kdrag/theories/fun.py
kdrag/theories/int.py
kdrag/theories/list.py
knuckledragger-0.1.3.dist-info/WHEEL
knuckledragger-0.1.3.dist-info/METADATA
knuckledragger-0.1.3.dist-info/RECORD
