Metadata-Version: 2.4
Name: knuckledragger
Version: 0.1.3
Summary: Interactive Theorem Prover
Author: Philip Zucker
Author-email: Philip Zucker <philzuckerblog@gmail.com>
License-Expression: MIT
Classifier: Programming Language :: Python :: 3
Classifier: Operating System :: OS Independent
Classifier: Topic :: Scientific/Engineering :: Mathematics
Classifier: Topic :: Software Development :: Disassemblers
Requires-Dist: z3-solver>=4.15.4
Requires-Dist: lark>=1.3.1
Requires-Dist: pytest>=6.0 ; extra == 'dev'
Requires-Dist: nbclient ; extra == 'dev'
Requires-Dist: jupyter ; extra == 'dev'
Requires-Dist: hypothesis>=6.124.1 ; extra == 'dev'
Requires-Dist: cle>=9.2.148 ; extra == 'pypcode'
Requires-Dist: pypcode>=3.0.3 ; extra == 'pypcode'
Requires-Dist: click>=8.1.8 ; extra == 'pypcode'
Requires-Dist: maturin>=1.8.6 ; extra == 'rust'
Requires-Dist: egglog>=9.0.0 ; extra == 'solvers'
Requires-Dist: python-flint ; extra == 'solvers'
Requires-Dist: sympy ; extra == 'solvers'
Requires-Dist: cffi>=2.0.0 ; extra == 'solvers'
Requires-Dist: graphviz>=0.20.3 ; extra == 'solvers'
Requires-Dist: yowasp-yosys>=0.50.0.0.post858 ; extra == 'yosys'
Requires-Python: >=3.12
Project-URL: homepage, https://github.com/philzook58/knuckledragger
Provides-Extra: dev
Provides-Extra: pypcode
Provides-Extra: rust
Provides-Extra: solvers
Provides-Extra: yosys
